MANIFEST.in
purchase_requisition_data.xml
purchase_requisition_demo.xml
purchase_requisition_report.xml
purchase_requisition_sequence.xml
purchase_requisition_view.xml
setup.py
./__init__.py
./__openerp__.py
./purchase_requisition.py
./report/__init__.py
./report/requisition.py
./wizard/__init__.py
./wizard/purchase_requisition_partner.py
i18n/ar.po
i18n/bg.po
i18n/bs.po
i18n/ca.po
i18n/cs.po
i18n/da.po
i18n/de.po
i18n/es.po
i18n/es_CR.po
i18n/es_MX.po
i18n/es_VE.po
i18n/fi.po
i18n/fr.po
i18n/hr.po
i18n/hu.po
i18n/id.po
i18n/it.po
i18n/ja.po
i18n/ko.po
i18n/mk.po
i18n/mn.po
i18n/nb.po
i18n/nl.po
i18n/pl.po
i18n/pt.po
i18n/pt_BR.po
i18n/purchase_requisition.pot
i18n/ro.po
i18n/ru.po
i18n/sl.po
i18n/sv.po
i18n/tr.po
i18n/zh_CN.po
images/purchase_requisitions.jpeg
openerp_purchase_requisition.egg-info/PKG-INFO
openerp_purchase_requisition.egg-info/SOURCES.txt
openerp_purchase_requisition.egg-info/dependency_links.txt
openerp_purchase_requisition.egg-info/requires.txt
openerp_purchase_requisition.egg-info/top_level.txt
report/purchase_requisition.rml
report/purchase_requisition.sxw
security/ir.model.access.csv
security/purchase_tender.xml
test/cancel_purchase_requisition.yml
test/purchase_requisition.yml
test/purchase_requisition_demo.yml
wizard/purchase_requisition_partner_view.xml